pyclicksign/__init__.py
pyclicksign/protocol.py
pyclicksign/sign.py
pyclicksign-0.0.4.dist-info/LICENSE
pyclicksign-0.0.4.dist-info/METADATA
pyclicksign-0.0.4.dist-info/WHEEL
pyclicksign-0.0.4.dist-info/top_level.txt
pyclicksign-0.0.4.dist-info/RECORD
