Metadata-Version: 2.1
Name: pyclicksign
Version: 0.0.4
Summary: Implementação da api rest da plataforma de assinaturas eletrônicas Clicksign.
Home-page: https://github.com/candango/pyclicksign
Author: Flavio Garcia
Author-email: piraz@candango.org
License: Apache License V2.0
Platform: UNKNOWN
Classifier: Development Status :: 1 - Planning
Classifier: Environment :: Console
Classifier: Environment :: Web Environment
Classifier: Intended Audience :: Developers
Classifier: Intended Audience :: System Administrators
Classifier: Programming Language :: Python :: 3
Classifier: Programming Language :: Python :: 3.6
Classifier: Programming Language :: Python :: 3.7
Classifier: Programming Language :: Python :: 3.8
Classifier: Programming Language :: Python :: 3.9
Classifier: Programming Language :: Python :: 3 :: Only
Classifier: Topic :: Software Development :: Libraries
License-File: LICENSE
Requires-Dist: filemagic (>=1.6)
Requires-Dist: firenado (>=0.2.14)
Requires-Dist: peasant (>=0.5)
